{
  "cuts": [
    {"cut": "baseline_electrons_n==0 && baseline_muons_n==0 && met>350 && jets_n==4 && bjets_n>=1 && bjets_n<=2 && dphi_sum4jet>2.6 && minv_bb>90 && minv_bb<150 && minv_non_bb>50 && minv_non_bb<120 && meff_4j > 500 && mct_bb > 280",
    "name": "metG350_nJetsEq4_nBJetsGeq1Leq2_dphiSum4jetG2p6_MinvbbG90L150_MinvNonbbG50L120_MeffG500_MctbbG280"},
    {"cut": "baseline_electrons_n==0 && baseline_muons_n==0 && met>350 && jets_n==4 && bjets_n>=1 && bjets_n_60<=2 && dphi_sum4jet>2.6 && minv_bb>90 && minv_bb<150 && minv_non_bb>50 && minv_non_bb<120 && meff_4j > 500 && mct_bb > 280",
    "name": "metG350_nJetsEq4_nBJets60Geq1Leq2_dphiSum4jetG2p6_MinvbbG90L150_MinvNonbbG50L120_MeffG500_MctbbG280"},
    {"cut": "baseline_electrons_n==0 && baseline_muons_n==0 && met>350 && jets_n==4 && bjets_n>=1 && bjets_n_70<=2 && dphi_sum4jet>2.6 && minv_bb>90 && minv_bb<150 && minv_non_bb>50 && minv_non_bb<120 && meff_4j > 500 && mct_bb > 280",
    "name": "metG350_nJetsEq4_nBJets70Geq1Leq2_dphiSum4jetG2p6_MinvbbG90L150_MinvNonbbG50L120_MeffG500_MctbbG280"},
    {"cut": "baseline_electrons_n==0 && baseline_muons_n==0 && met>350 && jets_n==4 && bjets_n>=1 && bjets_n_85<=2 && dphi_sum4jet>2.6 && minv_bb>90 && minv_bb<150 && minv_non_bb>50 && minv_non_bb<120 && meff_4j > 500 && mct_bb > 280",
    "name": "metG350_nJetsEq4_nBJets85Geq1Leq2_dphiSum4jetG2p6_MinvbbG90L150_MinvNonbbG50L120_MeffG500_MctbbG280"}
  ],
  "draw": [
    {
      "draw": "n_vtx",
      "name": "cutflow",
      "min": -1e8,
      "max": 1e8,
      "nbins": 1
    }
  ]
}
